pace/__init__.py
pace/pace.py
pace/utilfuncs.py
pace_mdgroup-0.1.1.dist-info/METADATA
pace_mdgroup-0.1.1.dist-info/WHEEL
pace_mdgroup-0.1.1.dist-info/top_level.txt
pace_mdgroup-0.1.1.dist-info/RECORD
