Metadata-Version: 2.4
Name: pace-mdgroup
Version: 0.1.1
Summary: Tools for the pace-mdgroup project.
Author-email: Mudit Dixit <dixitmuditg@gmail.com>
License: MIT
Project-URL: Homepage, https://github.com/dixitmudit/PACE
Project-URL: Repository, https://github.com/dixitmudit/PACE
Classifier: Programming Language :: Python :: 3
Classifier: License :: OSI Approved :: MIT License
Classifier: Operating System :: OS Independent
Requires-Python: >=3.9
